README.md
setup.py
my_api_plugin/__init__.py
my_api_plugin/api_client.py
my_api_plugin.egg-info/PKG-INFO
my_api_plugin.egg-info/SOURCES.txt
my_api_plugin.egg-info/dependency_links.txt
my_api_plugin.egg-info/requires.txt
my_api_plugin.egg-info/top_level.txt