Metadata-Version: 2.1
Name: my-api-plugin
Version: 0.1.1
Summary: A simple API plugin with POST requests
Home-page: https://github.com/yourusername/my_api_plugin
Author: Your Name
Author-email: your.email@example.com
License: UNKNOWN
Platform: UNKNOWN
